pythonic_toolbox/__init__.py
pythonic_toolbox/version.py
pythonic_toolbox/decorators/__init__.py
pythonic_toolbox/decorators/common.py
pythonic_toolbox/decorators/decorator_utils.py
pythonic_toolbox/utils/__init__.py
pythonic_toolbox/utils/context_utils.py
pythonic_toolbox/utils/deque_utils.py
pythonic_toolbox/utils/dict_utils.py
pythonic_toolbox/utils/functional_utils.py
pythonic_toolbox/utils/list_utils.py
pythonic_toolbox/utils/string_utils.py
pythonic_toolbox-1.1.40.dist-info/LICENSE.md
pythonic_toolbox-1.1.40.dist-info/METADATA
pythonic_toolbox-1.1.40.dist-info/WHEEL
pythonic_toolbox-1.1.40.dist-info/top_level.txt
pythonic_toolbox-1.1.40.dist-info/RECORD
