Metadata-Version: 2.1
Name: pythonic-toolbox
Version: 1.1.40
Summary: a toolbox with pythonic utils, tools
Home-page: https://github.com/albertmenglongli/pythonic-toolbox
Author: menglong.li
Author-email: albert.menglongli@gmail.com
License: Apache2.0
Keywords: toolbox
Platform: UNKNOWN
Classifier: Development Status :: 5 - Production/Stable
Classifier: Intended Audience :: Developers
Classifier: Topic :: Software Development :: Build Tools
Classifier: License :: OSI Approved :: MIT License
Classifier: Programming Language :: Python
Classifier: Programming Language :: Python :: 3
Classifier: Programming Language :: Python :: 3 :: Only
Classifier: Programming Language :: Python :: 3.6
Classifier: Programming Language :: Python :: 3.7
Classifier: Programming Language :: Python :: 3.8
Classifier: Programming Language :: Python :: 3.9
Classifier: Programming Language :: Python :: 3.10
Classifier: Programming Language :: Python :: 3.11
Classifier: Programming Language :: Python :: 3.12
Classifier: Topic :: Software Development :: Libraries :: Python Modules
License-File: LICENSE.md
Requires-Dist: setuptools
Requires-Dist: funcy (>=1.16)
Provides-Extra: test
Requires-Dist: pytest ; extra == 'test'
Requires-Dist: wheel ; extra == 'test'
